{
  "id": "7260456156357741850",
  "desc": "#AfD bald an der #Regierung? #Thüringen und #Deutschland, aufgepasst! Mit Björn #Höcke ist die #afdthüringen bestens vorbereitet, #Ramelow und Co. abzulösen. Der #ThüringerWeg ist der #Königsweg!  #SolPat #PohlPosition #Volksanwalt #Alternative #alternativefürdeutschland #Weidel",
  "createTime": "1690456697",
  "scheduleTime": 0,
  "video": {
    "id": "",
    "height": 576,
    "width": 1052,
    "duration": 109,
    "ratio": "540p",
    "cover": "https://p16-sign-useast2a.tiktokcdn.com/obj/tos-useast2a-p-0037-euttp/oYwAUBDlAxnaV6QwH8taeeEDbQPCOkQCpVIiEI?lk3s=81f88b70&x-expires=1737493200&x-signature=BthtGazSf7yAU6LTeMfTK9t3ODg%3D&shp=81f88b70&shcp=-",
    "originCover": "https://p16-sign-useast2a.tiktokcdn.com/obj/tos-useast2a-p-0037-euttp/058f8b8b2afd409ba762a7b456b48f1a_1690456698?lk3s=81f88b70&x-expires=1737493200&x-signature=R9f50Rbl8vVR6u4mwcwfxJ7UREM%3D&shp=81f88b70&shcp=-",
    "dynamicCover": "https://p16-sign-useast2a.tiktokcdn.com/obj/tos-useast2a-p-0037-euttp/b1224c19ff8046aeb6968f9912787a63_1690456699?lk3s=81f88b70&x-expires=1737493200&x-signature=jpzxfhlkeEK9j%2Br7YP53u0OqAWg%3D&shp=81f88b70&shcp=-",
    "playAddr": "https://v16-webapp-prime.us.tiktok.com/video/tos/useast2a/tos-useast2a-ve-0068c001-euttp/okw80nHQUbelDeibCQQEEPkSpWVawAPzDIVBgN/?a=1988&bti=ODszNWYuMDE6&ch=0&cr=3&dr=0&lr=all&cd=0%7C0%7C0%7C&cv=1&br=2084&bt=1042&cs=0&ds=6&ft=4KJMyMzm8Zmo0wjKHb4jVCauQpWrKsd.&mime_type=video_mp4&qs=0&rc=ZDppNjQ8OGQ2Z2Y7ZjVpaEBpM3JkMzs6ZnI4bTMzZjgzM0AuMmEuMy82NV8xLy01MGAtYSMybmVjcjRnMC5gLS1kL2Nzcw%3D%3D&btag=e00090000&expire=1737493700&l=2025011921063041F8462372A8480473EC&ply_type=2&policy=2&signature=cd0d601efc351046c1a2080a841abf76&tk=tt_chain_token",
    "downloadAddr": "",
    "shareCover": [
      ""
    ],
    "reflowCover": "",
    "bitrate": 1067773,
    "encodedType": "normal",
    "format": "mp4",
    "videoQuality": "normal",
    "encodeUserTag": "",
    "codecType": "h264",
    "definition": "540p",
    "subtitleInfos": [],
    "zoomCover": {
      "240": "https://p16-sign-useast2a.tiktokcdn.com/tos-useast2a-p-0037-euttp/oYwAUBDlAxnaV6QwH8taeeEDbQPCOkQCpVIiEI~tplv-photomode-zoomcover:240:240.avif?lk3s=81f88b70&x-expires=1737493200&x-signature=PDdoQHcoxHHltEPNRFaKRGf9FfE%3D&shp=81f88b70&shcp=-",
      "480": "https://p16-sign-useast2a.tiktokcdn.com/tos-useast2a-p-0037-euttp/oYwAUBDlAxnaV6QwH8taeeEDbQPCOkQCpVIiEI~tplv-photomode-zoomcover:480:480.avif?lk3s=81f88b70&x-expires=1737493200&x-signature=sx64b6iebUMboMQpmPuFHyJtHuw%3D&shp=81f88b70&shcp=-",
      "720": "https://p16-sign-useast2a.tiktokcdn.com/tos-useast2a-p-0037-euttp/oYwAUBDlAxnaV6QwH8taeeEDbQPCOkQCpVIiEI~tplv-photomode-zoomcover:720:720.avif?lk3s=81f88b70&x-expires=1737493200&x-signature=tgOi3NhoCrCdShPl%2BkV2TgvmOvU%3D&shp=81f88b70&shcp=-",
      "960": "https://p16-sign-useast2a.tiktokcdn.com/tos-useast2a-p-0037-euttp/oYwAUBDlAxnaV6QwH8taeeEDbQPCOkQCpVIiEI~tplv-photomode-zoomcover:960:960.avif?lk3s=81f88b70&x-expires=1737493200&x-signature=eDuFJrQ5oSPhQ3U3KfQ%2FoyrnAbo%3D&shp=81f88b70&shcp=-"
    },
    "volumeInfo": {
      "Loudness": -15.9,
      "Peak": 1
    },
    "bitrateInfo": [
      {
        "Bitrate": 1067773,
        "QualityType": 20,
        "GearName": "normal_540_0",
        "PlayAddr": {
          "DataSize": "14584451",
          "Width": 1052,
          "Height": 576,
          "Uri": "v0f025gc0000cj153ojc77u8f0haqo50",
          "UrlList": [
            "https://v16-webapp-prime.us.tiktok.com/video/tos/useast2a/tos-useast2a-ve-0068c001-euttp/okw80nHQUbelDeibCQQEEPkSpWVawAPzDIVBgN/?a=1988&bti=ODszNWYuMDE6&ch=0&cr=3&dr=0&lr=all&cd=0%7C0%7C0%7C&cv=1&br=2084&bt=1042&cs=0&ds=6&ft=4KJMyMzm8Zmo0wjKHb4jVCauQpWrKsd.&mime_type=video_mp4&qs=0&rc=ZDppNjQ8OGQ2Z2Y7ZjVpaEBpM3JkMzs6ZnI4bTMzZjgzM0AuMmEuMy82NV8xLy01MGAtYSMybmVjcjRnMC5gLS1kL2Nzcw%3D%3D&btag=e00090000&expire=1737493700&l=2025011921063041F8462372A8480473EC&ply_type=2&policy=2&signature=cd0d601efc351046c1a2080a841abf76&tk=tt_chain_token",
            "https://v19-webapp-prime.us.tiktok.com/video/tos/useast2a/tos-useast2a-ve-0068c001-euttp/okw80nHQUbelDeibCQQEEPkSpWVawAPzDIVBgN/?a=1988&bti=ODszNWYuMDE6&ch=0&cr=3&dr=0&lr=all&cd=0%7C0%7C0%7C&cv=1&br=2084&bt=1042&cs=0&ds=6&ft=4KJMyMzm8Zmo0wjKHb4jVCauQpWrKsd.&mime_type=video_mp4&qs=0&rc=ZDppNjQ8OGQ2Z2Y7ZjVpaEBpM3JkMzs6ZnI4bTMzZjgzM0AuMmEuMy82NV8xLy01MGAtYSMybmVjcjRnMC5gLS1kL2Nzcw%3D%3D&btag=e00090000&expire=1737493700&l=2025011921063041F8462372A8480473EC&ply_type=2&policy=2&signature=cd0d601efc351046c1a2080a841abf76&tk=tt_chain_token",
            "https://www.tiktok.com/aweme/v1/play/?faid=1988&file_id=0ecf328c082c4db38a95296113df571a&is_play_url=1&item_id=7260456156357741850&line=0&ply_type=2&signaturev3=dmlkZW9faWQ7ZmlsZV9pZDtpdGVtX2lkLmQ2NTcyNGI4OGI3YmUwNzFlZjdhZGEyOTg1YzMzMmNl&tk=tt_chain_token&video_id=v0f025gc0000cj153ojc77u8f0haqo50"
          ],
          "UrlKey": "v0f025gc0000cj153ojc77u8f0haqo50_h264_540p_1067773",
          "FileHash": "058d9caefe67f512f4eb7c983b672eaf",
          "FileCs": "c:0-90782-2e94"
        },
        "CodecType": "h264",
        "MVMAF": "\"\""
      },
      {
        "Bitrate": 657869,
        "QualityType": 14,
        "GearName": "adapt_lower_720_1",
        "PlayAddr": {
          "DataSize": "8985673",
          "Width": 1316,
          "Height": 720,
          "Uri": "v0f025gc0000cj153ojc77u8f0haqo50",
          "UrlList": [
            "https://v16-webapp-prime.us.tiktok.com/video/tos/useast2a/tos-useast2a-ve-0068c001-euttp/o4ElbgRUkfDb9wV5BQeDQHniCwAVi3IIQ8baPl/?a=1988&bti=ODszNWYuMDE6&ch=0&cr=3&dr=0&lr=all&cd=0%7C0%7C0%7C&cv=1&br=1284&bt=642&cs=2&ds=3&ft=4KJMyMzm8Zmo0wjKHb4jVCauQpWrKsd.&mime_type=video_mp4&qs=14&rc=Z2RnOTczMzQ1Ojk8Ozk4M0BpM3JkMzs6ZnI4bTMzZjgzM0AwNDYvXzYvXjYxXzNfLmEtYSMybmVjcjRnMC5gLS1kL2Nzcw%3D%3D&btag=e00090000&expire=1737493700&l=2025011921063041F8462372A8480473EC&ply_type=2&policy=2&signature=421c9b916767c118a56b4feb11d0d92c&tk=tt_chain_token",
            "https://v19-webapp-prime.us.tiktok.com/video/tos/useast2a/tos-useast2a-ve-0068c001-euttp/o4ElbgRUkfDb9wV5BQeDQHniCwAVi3IIQ8baPl/?a=1988&bti=ODszNWYuMDE6&ch=0&cr=3&dr=0&lr=all&cd=0%7C0%7C0%7C&cv=1&br=1284&bt=642&cs=2&ds=3&ft=4KJMyMzm8Zmo0wjKHb4jVCauQpWrKsd.&mime_type=video_mp4&qs=14&rc=Z2RnOTczMzQ1Ojk8Ozk4M0BpM3JkMzs6ZnI4bTMzZjgzM0AwNDYvXzYvXjYxXzNfLmEtYSMybmVjcjRnMC5gLS1kL2Nzcw%3D%3D&btag=e00090000&expire=1737493700&l=2025011921063041F8462372A8480473EC&ply_type=2&policy=2&signature=421c9b916767c118a56b4feb11d0d92c&tk=tt_chain_token",
            "https://www.tiktok.com/aweme/v1/play/?faid=1988&file_id=00d516b869b64792a12090b4269d7a3d&is_play_url=1&item_id=7260456156357741850&line=0&ply_type=2&signaturev3=dmlkZW9faWQ7ZmlsZV9pZDtpdGVtX2lkLjA5ZDIyYTk5Y2VmNWMwMjJlNjVhOGJmNTAzNWY5NjU4&tk=tt_chain_token&video_id=v0f025gc0000cj153ojc77u8f0haqo50"
          ],
          "UrlKey": "v0f025gc0000cj153ojc77u8f0haqo50_bytevc1_720p_657869",
          "FileHash": "c85821b491dc9dad8c0c045ee54875b5",
          "FileCs": "c:0-91475-1a3f"
        },
        "CodecType": "h265_hvc1",
        "MVMAF": "\"\""
      },
      {
        "Bitrate": 601965,
        "QualityType": 24,
        "GearName": "lower_540_0",
        "PlayAddr": {
          "DataSize": "8222094",
          "Width": 1052,
          "Height": 576,
          "Uri": "v0f025gc0000cj153ojc77u8f0haqo50",
          "UrlList": [
            "https://v16-webapp-prime.us.tiktok.com/video/tos/useast2a/tos-useast2a-ve-0068-euttp/oA2HIPKeinAoUCHw1leQDVkQ3CtQYBwwEKbzCD/?a=1988&bti=ODszNWYuMDE6&ch=0&cr=3&dr=0&lr=all&cd=0%7C0%7C0%7C&cv=1&br=1174&bt=587&cs=0&ds=6&ft=4KJMyMzm8Zmo0wjKHb4jVCauQpWrKsd.&mime_type=video_mp4&qs=4&rc=OWhlNDNmZDpmM2Y8Zjc8N0BpM3JkMzs6ZnI4bTMzZjgzM0BjYS4vNC8vNS4xXmBjMGA2YSMybmVjcjRnMC5gLS1kL2Nzcw%3D%3D&btag=e00090000&expire=1737493700&l=2025011921063041F8462372A8480473EC&ply_type=2&policy=2&signature=88c4184508a57f5c4f097fe7d950a9f4&tk=tt_chain_token",
            "https://v19-webapp-prime.us.tiktok.com/video/tos/useast2a/tos-useast2a-ve-0068-euttp/oA2HIPKeinAoUCHw1leQDVkQ3CtQYBwwEKbzCD/?a=1988&bti=ODszNWYuMDE6&ch=0&cr=3&dr=0&lr=all&cd=0%7C0%7C0%7C&cv=1&br=1174&bt=587&cs=0&ds=6&ft=4KJMyMzm8Zmo0wjKHb4jVCauQpWrKsd.&mime_type=video_mp4&qs=4&rc=OWhlNDNmZDpmM2Y8Zjc8N0BpM3JkMzs6ZnI4bTMzZjgzM0BjYS4vNC8vNS4xXmBjMGA2YSMybmVjcjRnMC5gLS1kL2Nzcw%3D%3D&btag=e00090000&expire=1737493700&l=2025011921063041F8462372A8480473EC&ply_type=2&policy=2&signature=88c4184508a57f5c4f097fe7d950a9f4&tk=tt_chain_token",
            "https://www.tiktok.com/aweme/v1/play/?faid=1988&file_id=94c934fcc9ac401c872a2c70211bdef6&is_play_url=1&item_id=7260456156357741850&line=0&ply_type=2&signaturev3=dmlkZW9faWQ7ZmlsZV9pZDtpdGVtX2lkLjRhZGVkZWQ1OWYxMGZmYzIyZDk5MDlkOGJiOGFlNjNj&tk=tt_chain_token&video_id=v0f025gc0000cj153ojc77u8f0haqo50"
          ],
          "UrlKey": "v0f025gc0000cj153ojc77u8f0haqo50_h264_540p_601965",
          "FileHash": "62127607b87fe1570930d01dcdda193b",
          "FileCs": "c:0-90782-36c3"
        },
        "CodecType": "h264",
        "MVMAF": "\"\""
      },
      {
        "Bitrate": 510453,
        "QualityType": 28,
        "GearName": "adapt_540_1",
        "PlayAddr": {
          "DataSize": "6972151",
          "Width": 1052,
          "Height": 576,
          "Uri": "v0f025gc0000cj153ojc77u8f0haqo50",
          "UrlList": [
            "https://v16-webapp-prime.us.tiktok.com/video/tos/useast2a/tos-useast2a-ve-0068-euttp/oobVICHeKQiqjGC5YdBtExKlQQecDkAlwtnPpD/?a=1988&bti=ODszNWYuMDE6&ch=0&cr=3&dr=0&lr=all&cd=0%7C0%7C0%7C&cv=1&br=996&bt=498&cs=2&ds=6&ft=4KJMyMzm8Zmo0wjKHb4jVCauQpWrKsd.&mime_type=video_mp4&qs=11&rc=ZzlpN2RmZmg8aDhnaWZpaUBpM3JkMzs6ZnI4bTMzZjgzM0AyYi1gMTJfXzUxNmNiMzEuYSMybmVjcjRnMC5gLS1kL2Nzcw%3D%3D&btag=e00090000&expire=1737493700&l=2025011921063041F8462372A8480473EC&ply_type=2&policy=2&signature=03f908b5b5e4a182f0d96a7d94fedc5f&tk=tt_chain_token",
            "https://v19-webapp-prime.us.tiktok.com/video/tos/useast2a/tos-useast2a-ve-0068-euttp/oobVICHeKQiqjGC5YdBtExKlQQecDkAlwtnPpD/?a=1988&bti=ODszNWYuMDE6&ch=0&cr=3&dr=0&lr=all&cd=0%7C0%7C0%7C&cv=1&br=996&bt=498&cs=2&ds=6&ft=4KJMyMzm8Zmo0wjKHb4jVCauQpWrKsd.&mime_type=video_mp4&qs=11&rc=ZzlpN2RmZmg8aDhnaWZpaUBpM3JkMzs6ZnI4bTMzZjgzM0AyYi1gMTJfXzUxNmNiMzEuYSMybmVjcjRnMC5gLS1kL2Nzcw%3D%3D&btag=e00090000&expire=1737493700&l=2025011921063041F8462372A8480473EC&ply_type=2&policy=2&signature=03f908b5b5e4a182f0d96a7d94fedc5f&tk=tt_chain_token",
            "https://www.tiktok.com/aweme/v1/play/?faid=1988&file_id=1f4f6ceffd954e89bebc5c4ac40fe65d&is_play_url=1&item_id=7260456156357741850&line=0&ply_type=2&signaturev3=dmlkZW9faWQ7ZmlsZV9pZDtpdGVtX2lkLmQzYWQxOTE0NzQzYjBkY2VmZTIxMDQ0YzhjMThiZWU0&tk=tt_chain_token&video_id=v0f025gc0000cj153ojc77u8f0haqo50"
          ],
          "UrlKey": "v0f025gc0000cj153ojc77u8f0haqo50_bytevc1_540p_510453",
          "FileHash": "f5927b64e77ea15d91c47bbbf7528961",
          "FileCs": "c:0-91475-ed96"
        },
        "CodecType": "h265_hvc1",
        "MVMAF": "\"\""
      }
    ],
    "VQScore": "64.98",
    "claInfo": {
      "hasOriginalAudio": false,
      "enableAutoCaption": true,
      "captionInfos": [],
      "noCaptionReason": 3
    }
  },
  "author": {
    "id": "6921665740072633346",
    "shortId": "",
    "uniqueId": "juergenpohlafd",
    "nickname": "Jürgen Pohl",
    "avatarLarger": "https://p16-sign-va.tiktokcdn.com/tos-maliva-avt-0068/49dbd8ec633edfcdcabdd7664cc6006d~c5_1080x1080.jpeg?lk3s=a5d48078&nonce=15281&refresh_token=f2300aaa99e1a11c763d6b2f979fda14&x-expires=1737493200&x-signature=eYEmgHyF4%2F2zINq5KQA%2F%2FHTpnHM%3D&shp=a5d48078&shcp=81f88b70",
    "avatarMedium": "https://p16-sign-va.tiktokcdn.com/tos-maliva-avt-0068/49dbd8ec633edfcdcabdd7664cc6006d~c5_720x720.jpeg?lk3s=a5d48078&nonce=42381&refresh_token=2a58a7e747deac4979575be08bd73370&x-expires=1737493200&x-signature=HZwjUt2I51q5kjRBHihSNjPQbbM%3D&shp=a5d48078&shcp=81f88b70",
    "avatarThumb": "https://p16-sign-va.tiktokcdn.com/tos-maliva-avt-0068/49dbd8ec633edfcdcabdd7664cc6006d~c5_100x100.jpeg?lk3s=a5d48078&nonce=76995&refresh_token=e09c5e33e9af3786b4cb8f94bc812ac5&x-expires=1737493200&x-signature=kaJCiLd0b8RQtekOaCFBVuj%2FfJc%3D&shp=a5d48078&shcp=81f88b70",
    "signature": "Mitglied des Deutschen Bundestages",
    "createTime": 0,
    "verified": false,
    "secUid": "MS4wLjABAAAAyLVlvnTcIX7ucy4nHraDIJw44tnR240LExSZ-x6dvlPbpuao2cSVWf-AIWMD0K4_",
    "ftc": false,
    "relation": 0,
    "openFavorite": false,
    "commentSetting": 0,
    "duetSetting": 0,
    "stitchSetting": 0,
    "privateAccount": false,
    "secret": false,
    "isADVirtual": false,
    "roomId": "",
    "uniqueIdModifyTime": 0,
    "ttSeller": false,
    "downloadSetting": 3,
    "recommendReason": "",
    "nowInvitationCardUrl": "",
    "nickNameModifyTime": 0,
    "isEmbedBanned": false,
    "canExpPlaylist": false,
    "suggestAccountBind": false
  },
  "music": {
    "id": "7260456177669409562",
    "title": "Originalton - Jürgen Pohl",
    "playUrl": "https://v19.tiktokcdn-us.com/e999cc1aa74dee7c4d8b0e5cbf0c618f/678dbe24/video/tos/useast2a/tos-useast2a-v-2370-euttp/o4zNqhNQkMUY9fgKEnKtzuMoEyBXAEopCyISBh/?a=1233&bti=ODszNWYuMDE6&ch=0&cr=0&dr=0&er=0&lr=default&cd=0%7C0%7C0%7C0&br=250&bt=125&ft=GSDrKInz7ThoqYkOXq8Zmo&mime_type=audio_mpeg&qs=6&rc=ZWg3ZDRmZTRlaDQ2NzxoOUBpajd1bWc6Zng4bTMzZjU8M0AwNTYtXzQxNmIxMmNeNC4uYSNfMWFocjRvMS5gLS1kMWNzcw%3D%3D&vvpl=1&l=2025011921063041F8462372A8480473EC&btag=e00090000",
    "coverLarge": "https://p16-sign-va.tiktokcdn.com/tos-maliva-avt-0068/49dbd8ec633edfcdcabdd7664cc6006d~c5_1080x1080.jpeg?lk3s=a5d48078&nonce=15281&refresh_token=f2300aaa99e1a11c763d6b2f979fda14&x-expires=1737493200&x-signature=eYEmgHyF4%2F2zINq5KQA%2F%2FHTpnHM%3D&shp=a5d48078&shcp=81f88b70",
    "coverMedium": "https://p16-sign-va.tiktokcdn.com/tos-maliva-avt-0068/49dbd8ec633edfcdcabdd7664cc6006d~c5_720x720.jpeg?lk3s=a5d48078&nonce=42381&refresh_token=2a58a7e747deac4979575be08bd73370&x-expires=1737493200&x-signature=HZwjUt2I51q5kjRBHihSNjPQbbM%3D&shp=a5d48078&shcp=81f88b70",
    "coverThumb": "https://p16-sign-va.tiktokcdn.com/tos-maliva-avt-0068/49dbd8ec633edfcdcabdd7664cc6006d~c5_100x100.jpeg?lk3s=a5d48078&nonce=76995&refresh_token=e09c5e33e9af3786b4cb8f94bc812ac5&x-expires=1737493200&x-signature=kaJCiLd0b8RQtekOaCFBVuj%2FfJc%3D&shp=a5d48078&shcp=81f88b70",
    "authorName": "Jürgen Pohl",
    "original": false,
    "duration": 109,
    "scheduleSearchTime": 0,
    "collected": false,
    "preciseDuration": {
      "preciseDuration": 109.29631,
      "preciseShootDuration": 109.29631,
      "preciseAuditionDuration": 109.29631,
      "preciseVideoDuration": 109.29631
    },
    "isCopyrighted": false
  },
  "challenges": [
    {
      "id": "6391435",
      "title": "afd",
      "desc": "",
      "profileLarger": "",
      "profileMedium": "",
      "profileThumb": "",
      "coverLarger": "",
      "coverMedium": "",
      "coverThumb": ""
    },
    {
      "id": "65758790",
      "title": "regierung",
      "desc": "",
      "profileLarger": "",
      "profileMedium": "",
      "profileThumb": "",
      "coverLarger": "",
      "coverMedium": "",
      "coverThumb": ""
    },
    {
      "id": "9321523",
      "title": "thüringen",
      "desc": "",
      "profileLarger": "",
      "profileMedium": "",
      "profileThumb": "",
      "coverLarger": "",
      "coverMedium": "",
      "coverThumb": ""
    },
    {
      "id": "204862",
      "title": "deutschland",
      "desc": "🇩🇪  musical.ly Deutschland 🇩🇪\n\nGib uns ein LIKE und werde mit etwas Glück gefeatured!!! 💛\n\nFür Features den Hashtag #Deutschland nicht vergessen! ☝",
      "profileLarger": "",
      "profileMedium": "",
      "profileThumb": "",
      "coverLarger": "",
      "coverMedium": "",
      "coverThumb": ""
    },
    {
      "id": "1657808367154181",
      "title": "höcke",
      "desc": "",
      "profileLarger": "",
      "profileMedium": "",
      "profileThumb": "",
      "coverLarger": "",
      "coverMedium": "",
      "coverThumb": ""
    },
    {
      "id": "1688427461573633",
      "title": "afdthüringen",
      "desc": "",
      "profileLarger": "",
      "profileMedium": "",
      "profileThumb": "",
      "coverLarger": "",
      "coverMedium": "",
      "coverThumb": ""
    },
    {
      "id": "1634457955024901",
      "title": "ramelow",
      "desc": "",
      "profileLarger": "",
      "profileMedium": "",
      "profileThumb": "",
      "coverLarger": "",
      "coverMedium": "",
      "coverThumb": ""
    },
    {
      "id": "7260455848307064858",
      "title": "thüringerweg",
      "desc": "",
      "profileLarger": "",
      "profileMedium": "",
      "profileThumb": "",
      "coverLarger": "",
      "coverMedium": "",
      "coverThumb": ""
    },
    {
      "id": "1665756414569478",
      "title": "königsweg",
      "desc": "",
      "profileLarger": "",
      "profileMedium": "",
      "profileThumb": "",
      "coverLarger": "",
      "coverMedium": "",
      "coverThumb": ""
    },
    {
      "id": "24216130",
      "title": "solpat",
      "desc": "",
      "profileLarger": "",
      "profileMedium": "",
      "profileThumb": "",
      "coverLarger": "",
      "coverMedium": "",
      "coverThumb": ""
    },
    {
      "id": "1703208065763334",
      "title": "pohlposition",
      "desc": "",
      "profileLarger": "",
      "profileMedium": "",
      "profileThumb": "",
      "coverLarger": "",
      "coverMedium": "",
      "coverThumb": ""
    },
    {
      "id": "7200651797730426886",
      "title": "volksanwalt",
      "desc": "",
      "profileLarger": "",
      "profileMedium": "",
      "profileThumb": "",
      "coverLarger": "",
      "coverMedium": "",
      "coverThumb": ""
    },
    {
      "id": "6500",
      "title": "alternative",
      "desc": "",
      "profileLarger": "",
      "profileMedium": "",
      "profileThumb": "",
      "coverLarger": "",
      "coverMedium": "",
      "coverThumb": ""
    },
    {
      "id": "1636682243342342",
      "title": "alternativefürdeutschland",
      "desc": "",
      "profileLarger": "",
      "profileMedium": "",
      "profileThumb": "",
      "coverLarger": "",
      "coverMedium": "",
      "coverThumb": ""
    },
    {
      "id": "1611616932459525",
      "title": "weidel",
      "desc": "",
      "profileLarger": "",
      "profileMedium": "",
      "profileThumb": "",
      "coverLarger": "",
      "coverMedium": "",
      "coverThumb": ""
    }
  ],
  "stats": {
    "diggCount": 84,
    "shareCount": 9,
    "commentCount": 0,
    "playCount": 918,
    "collectCount": "0"
  },
  "statsV2": {
    "diggCount": "84",
    "shareCount": "9",
    "commentCount": "0",
    "playCount": "918",
    "collectCount": "0",
    "repostCount": "0"
  },
  "warnInfo": [],
  "originalItem": false,
  "officalItem": false,
  "textExtra": [
    {
      "awemeId": "",
      "start": 0,
      "end": 4,
      "hashtagId": "6391435",
      "hashtagName": "afd",
      "type": 1,
      "subType": 0,
      "isCommerce": false
    },
    {
      "awemeId": "",
      "start": 17,
      "end": 27,
      "hashtagId": "65758790",
      "hashtagName": "regierung",
      "type": 1,
      "subType": 0,
      "isCommerce": false
    },
    {
      "awemeId": "",
      "start": 29,
      "end": 39,
      "hashtagId": "9321523",
      "hashtagName": "thüringen",
      "type": 1,
      "subType": 0,
      "isCommerce": false
    },
    {
      "awemeId": "",
      "start": 44,
      "end": 56,
      "hashtagId": "204862",
      "hashtagName": "deutschland",
      "type": 1,
      "subType": 0,
      "isCommerce": false
    },
    {
      "awemeId": "",
      "start": 80,
      "end": 86,
      "hashtagId": "1657808367154181",
      "hashtagName": "höcke",
      "type": 1,
      "subType": 0,
      "isCommerce": false
    },
    {
      "awemeId": "",
      "start": 95,
      "end": 108,
      "hashtagId": "1688427461573633",
      "hashtagName": "afdthüringen",
      "type": 1,
      "subType": 0,
      "isCommerce": false
    },
    {
      "awemeId": "",
      "start": 130,
      "end": 138,
      "hashtagId": "1634457955024901",
      "hashtagName": "ramelow",
      "type": 1,
      "subType": 0,
      "isCommerce": false
    },
    {
      "awemeId": "",
      "start": 162,
      "end": 175,
      "hashtagId": "7260455848307064858",
      "hashtagName": "thüringerweg",
      "type": 1,
      "subType": 0,
      "isCommerce": false
    },
    {
      "awemeId": "",
      "start": 184,
      "end": 194,
      "hashtagId": "1665756414569478",
      "hashtagName": "königsweg",
      "type": 1,
      "subType": 0,
      "isCommerce": false
    },
    {
      "awemeId": "",
      "start": 197,
      "end": 204,
      "hashtagId": "24216130",
      "hashtagName": "solpat",
      "type": 1,
      "subType": 0,
      "isCommerce": false
    },
    {
      "awemeId": "",
      "start": 205,
      "end": 218,
      "hashtagId": "1703208065763334",
      "hashtagName": "pohlposition",
      "type": 1,
      "subType": 0,
      "isCommerce": false
    },
    {
      "awemeId": "",
      "start": 219,
      "end": 231,
      "hashtagId": "7200651797730426886",
      "hashtagName": "volksanwalt",
      "type": 1,
      "subType": 0,
      "isCommerce": false
    },
    {
      "awemeId": "",
      "start": 232,
      "end": 244,
      "hashtagId": "6500",
      "hashtagName": "alternative",
      "type": 1,
      "subType": 0,
      "isCommerce": false
    },
    {
      "awemeId": "",
      "start": 245,
      "end": 271,
      "hashtagId": "1636682243342342",
      "hashtagName": "alternativefürdeutschland",
      "type": 1,
      "subType": 0,
      "isCommerce": false
    },
    {
      "awemeId": "",
      "start": 272,
      "end": 279,
      "hashtagId": "1611616932459525",
      "hashtagName": "weidel",
      "type": 1,
      "subType": 0,
      "isCommerce": false
    }
  ],
  "secret": false,
  "forFriend": false,
  "digged": false,
  "itemCommentStatus": 3,
  "takeDown": 0,
  "effectStickers": [],
  "authorStats": {
    "followerCount": 4775,
    "followingCount": 5,
    "heart": 30900,
    "heartCount": 30900,
    "videoCount": 161,
    "diggCount": 31,
    "friendCount": 0
  },
  "privateItem": false,
  "stickersOnItem": [],
  "shareEnabled": true,
  "comments": [],
  "duetDisplay": 0,
  "stitchDisplay": 0,
  "indexEnabled": true,
  "locationCreated": "DE",
  "suggestedWords": [],
  "contents": [
    {
      "desc": "#AfD bald an der #Regierung? #Thüringen und #Deutschland, aufgepasst!",
      "textExtra": [
        {
          "awemeId": "",
          "start": 0,
          "end": 4,
          "hashtagId": "6391435",
          "hashtagName": "afd",
          "type": 1,
          "subType": 0,
          "isCommerce": false
        },
        {
          "awemeId": "",
          "start": 17,
          "end": 27,
          "hashtagId": "65758790",
          "hashtagName": "regierung",
          "type": 1,
          "subType": 0,
          "isCommerce": false
        },
        {
          "awemeId": "",
          "start": 29,
          "end": 39,
          "hashtagId": "9321523",
          "hashtagName": "thüringen",
          "type": 1,
          "subType": 0,
          "isCommerce": false
        },
        {
          "awemeId": "",
          "start": 44,
          "end": 56,
          "hashtagId": "204862",
          "hashtagName": "deutschland",
          "type": 1,
          "subType": 0,
          "isCommerce": false
        }
      ]
    },
    {
      "desc": "",
      "textExtra": []
    },
    {
      "desc": "Mit Björn #Höcke ist die #afdthüringen bestens vorbereitet, #Ramelow und Co. abzulösen. Der #ThüringerWeg ist der #Königsweg! ",
      "textExtra": [
        {
          "awemeId": "",
          "start": 10,
          "end": 16,
          "hashtagId": "1657808367154181",
          "hashtagName": "höcke",
          "type": 1,
          "subType": 0,
          "isCommerce": false
        },
        {
          "awemeId": "",
          "start": 25,
          "end": 38,
          "hashtagId": "1688427461573633",
          "hashtagName": "afdthüringen",
          "type": 1,
          "subType": 0,
          "isCommerce": false
        },
        {
          "awemeId": "",
          "start": 60,
          "end": 68,
          "hashtagId": "1634457955024901",
          "hashtagName": "ramelow",
          "type": 1,
          "subType": 0,
          "isCommerce": false
        },
        {
          "awemeId": "",
          "start": 92,
          "end": 105,
          "hashtagId": "7260455848307064858",
          "hashtagName": "thüringerweg",
          "type": 1,
          "subType": 0,
          "isCommerce": false
        },
        {
          "awemeId": "",
          "start": 114,
          "end": 124,
          "hashtagId": "1665756414569478",
          "hashtagName": "königsweg",
          "type": 1,
          "subType": 0,
          "isCommerce": false
        }
      ]
    },
    {
      "desc": "",
      "textExtra": []
    },
    {
      "desc": "#SolPat #PohlPosition #Volksanwalt #Alternative #alternativefürdeutschland #Weidel",
      "textExtra": [
        {
          "awemeId": "",
          "start": 0,
          "end": 7,
          "hashtagId": "24216130",
          "hashtagName": "solpat",
          "type": 1,
          "subType": 0,
          "isCommerce": false
        },
        {
          "awemeId": "",
          "start": 8,
          "end": 21,
          "hashtagId": "1703208065763334",
          "hashtagName": "pohlposition",
          "type": 1,
          "subType": 0,
          "isCommerce": false
        },
        {
          "awemeId": "",
          "start": 22,
          "end": 34,
          "hashtagId": "7200651797730426886",
          "hashtagName": "volksanwalt",
          "type": 1,
          "subType": 0,
          "isCommerce": false
        },
        {
          "awemeId": "",
          "start": 35,
          "end": 47,
          "hashtagId": "6500",
          "hashtagName": "alternative",
          "type": 1,
          "subType": 0,
          "isCommerce": false
        },
        {
          "awemeId": "",
          "start": 48,
          "end": 74,
          "hashtagId": "1636682243342342",
          "hashtagName": "alternativefürdeutschland",
          "type": 1,
          "subType": 0,
          "isCommerce": false
        },
        {
          "awemeId": "",
          "start": 75,
          "end": 82,
          "hashtagId": "1611616932459525",
          "hashtagName": "weidel",
          "type": 1,
          "subType": 0,
          "isCommerce": false
        }
      ]
    }
  ],
  "diversificationId": 10083,
  "collected": false,
  "channelTags": [],
  "item_control": {
    "can_repost": true
  },
  "IsAigc": false,
  "AIGCDescription": "",
  "backendSourceEventTracking": "",
  "CategoryType": 120,
  "textLanguage": "de",
  "textTranslatable": true
}