{
	"id": "kcDom8eohnB3ITF",
	"json": "{\"id\":\"kcDom8eohnB3ITF\",\"url\":\"https://www.tiktok.com/@afdcommunity/photo/7386736679714835744\",\"loadedUrl\":\"https://www.tiktok.com/@afdcommunity/photo/7386736679714835744\",\"uniqueKey\":\"https://www.tiktok.com/@afdcommunity/photo/7386736679714835744\",\"method\":\"GET\",\"noRetry\":false,\"retryCount\":0,\"errorMessages\":[],\"headers\":{},\"userData\":{\"__crawlee\":{\"state\":4}},\"handledAt\":\"2024-11-12T14:14:49.682Z\"}",
	"method": "GET",
	"orderNo": null,
	"retryCount": 0,
	"uniqueKey": "https://www.tiktok.com/@afdcommunity/photo/7386736679714835744",
	"url": "https://www.tiktok.com/@afdcommunity/photo/7386736679714835744"
}