{
  "id": "7418891684420930849",
  "desc": "26.09.24 Aktuelle Stunde im Bundestag. Stefan Brandener AfD. #afd #afddeutschland #afdbundestag #stefanbrandner #bundestag #ampelregierungmussweg # #bürokratieentlastungsgesetz #aktuell #deutschland #fürdich #fyp #politik #politiktiktok ",
  "createTime": "1727345338",
  "scheduleTime": 0,
  "video": {
    "id": "",
    "height": 1026,
    "width": 576,
    "duration": 328,
    "ratio": "540p",
    "cover": "https://p16-sign-useast2a.tiktokcdn.com/obj/tos-useast2a-p-0037-euttp/ogrIpiPcZjU0CDXEUV7TATEwWB8yv1SOMvAiB?lk3s=81f88b70&x-expires=1733508000&x-signature=9Vjyj8%2BFMYrC5OZMCAn9NdVNbNY%3D&shp=81f88b70&shcp=-",
    "originCover": "https://p16-sign-useast2a.tiktokcdn.com/obj/tos-useast2a-p-0037-euttp/390e4ce2a2de47ae9161023b86d94935_1727345355?lk3s=81f88b70&x-expires=1733508000&x-signature=CAbp4jHyF3cIVGUCQzD8h931d1g%3D&shp=81f88b70&shcp=-",
    "dynamicCover": "https://p16-sign-useast2a.tiktokcdn.com/obj/tos-useast2a-p-0037-euttp/a3611fc3b8c245a7ad439ac81d5d29e9_1727345356?lk3s=81f88b70&x-expires=1733508000&x-signature=GCYY1ydv69OZFYS5r6cgbYmFF%2Bg%3D&shp=81f88b70&shcp=-",
    "playAddr": "https://v16-webapp-prime.tiktok.com/video/tos/useast2a/tos-useast2a-ve-0068c001-euttp/oEZIJL7IIRfggG6dlqe6UshAjZsfNGeJGAliEd/?a=1988&bti=ODszNWYuMDE6&ch=0&cr=3&dr=0&lr=all&cd=0%7C0%7C0%7C&cv=1&br=554&bt=277&cs=0&ds=6&ft=4fUEKMFx8Zmo0KhCqb4jVk7CrpWrKsd.&mime_type=video_mp4&qs=0&rc=OGU0O2Y0OWY2NmZoZzk5aEBpamw8aGw5cm5sdTMzZjczM0A0MDZjYmNeNmMxNGAyLTQvYSNeYmw0MmQ0cm5gLS1kMWNzcw%3D%3D&btag=e000a0000&expire=1733357218&l=202412041801294B1E5C8317906016A952&ply_type=2&policy=2&signature=a26e3286cef3a6e2a71d72708b02afa0&tk=tt_chain_token",
    "downloadAddr": "",
    "shareCover": [
      ""
    ],
    "reflowCover": "",
    "bitrate": 283859,
    "encodedType": "normal",
    "format": "mp4",
    "videoQuality": "normal",
    "encodeUserTag": "",
    "codecType": "h264",
    "definition": "540p",
    "subtitleInfos": [
      {
        "UrlExpire": "1733357218",
        "Size": "10343",
        "LanguageID": "20",
        "LanguageCodeName": "deu-DE",
        "Url": "https://v16-webapp.tiktok.com/920a53af7877fe079937ab6d267fb4d9/6750eea2/video/tos/useast2a/tos-useast2a-v-0037-euttp/d07377531a1e4639b55cac8414cebe39/?a=1988&bti=ODszNWYuMDE6&ch=0&cr=3&dr=0&lr=all&cd=0%7C0%7C0%7C&cv=1&br=6700&bt=3350&ds=4&ft=4b~OyMFx8Zmo0KhCqb4jVk7CrpWrKsd.&mime_type=video_mp4&qs=13&rc=amw8aGw5cm5sdTMzZjczM0Bpamw8aGw5cm5sdTMzZjczM0BeYmw0MmQ0cm5gLS1kMWNzYSNeYmw0MmQ0cm5gLS1kMWNzcw%3D%3D&l=202412041801294B1E5C8317906016A952&btag=e00060000",
        "Format": "webvtt",
        "Version": "1:whisper_lid",
        "Source": "ASR"
      }
    ],
    "zoomCover": {
      "240": "https://p16-sign-useast2a.tiktokcdn.com/tos-useast2a-p-0037-euttp/ogrIpiPcZjU0CDXEUV7TATEwWB8yv1SOMvAiB~tplv-photomode-zoomcover:240:240.avif?lk3s=81f88b70&x-expires=1733508000&x-signature=siLs2TOYJqkxfR4QxwFy%2FKYDAGU%3D&shp=81f88b70&shcp=-",
      "480": "https://p16-sign-useast2a.tiktokcdn.com/tos-useast2a-p-0037-euttp/ogrIpiPcZjU0CDXEUV7TATEwWB8yv1SOMvAiB~tplv-photomode-zoomcover:480:480.avif?lk3s=81f88b70&x-expires=1733508000&x-signature=NIBawcVlrolaa4l%2B8eR5WTpGk6o%3D&shp=81f88b70&shcp=-",
      "720": "https://p16-sign-useast2a.tiktokcdn.com/tos-useast2a-p-0037-euttp/ogrIpiPcZjU0CDXEUV7TATEwWB8yv1SOMvAiB~tplv-photomode-zoomcover:720:720.avif?lk3s=81f88b70&x-expires=1733508000&x-signature=lYXKtWwJTtsoTObboIQ9%2FXvYTk4%3D&shp=81f88b70&shcp=-",
      "960": "https://p16-sign-useast2a.tiktokcdn.com/tos-useast2a-p-0037-euttp/ogrIpiPcZjU0CDXEUV7TATEwWB8yv1SOMvAiB~tplv-photomode-zoomcover:960:960.avif?lk3s=81f88b70&x-expires=1733508000&x-signature=F4evgaangns3yE1mfe9OOPBkDj0%3D&shp=81f88b70&shcp=-"
    },
    "volumeInfo": {
      "Loudness": -26,
      "Peak": 0.23988
    },
    "bitrateInfo": [
      {
        "Bitrate": 283859,
        "QualityType": 20,
        "GearName": "normal_540_0",
        "PlayAddr": {
          "DataSize": "11640073",
          "Width": 576,
          "Height": 1026,
          "Uri": "v0f044gc0000crqiuk7og65i7eo9eiag",
          "UrlList": [
            "https://v16-webapp-prime.tiktok.com/video/tos/useast2a/tos-useast2a-ve-0068c001-euttp/oEZIJL7IIRfggG6dlqe6UshAjZsfNGeJGAliEd/?a=1988&bti=ODszNWYuMDE6&ch=0&cr=3&dr=0&lr=all&cd=0%7C0%7C0%7C&cv=1&br=554&bt=277&cs=0&ds=6&ft=4fUEKMFx8Zmo0KhCqb4jVk7CrpWrKsd.&mime_type=video_mp4&qs=0&rc=OGU0O2Y0OWY2NmZoZzk5aEBpamw8aGw5cm5sdTMzZjczM0A0MDZjYmNeNmMxNGAyLTQvYSNeYmw0MmQ0cm5gLS1kMWNzcw%3D%3D&btag=e000a0000&expire=1733357218&l=202412041801294B1E5C8317906016A952&ply_type=2&policy=2&signature=a26e3286cef3a6e2a71d72708b02afa0&tk=tt_chain_token",
            "https://v19-webapp-prime.tiktok.com/video/tos/useast2a/tos-useast2a-ve-0068c001-euttp/oEZIJL7IIRfggG6dlqe6UshAjZsfNGeJGAliEd/?a=1988&bti=ODszNWYuMDE6&ch=0&cr=3&dr=0&lr=all&cd=0%7C0%7C0%7C&cv=1&br=554&bt=277&cs=0&ds=6&ft=4fUEKMFx8Zmo0KhCqb4jVk7CrpWrKsd.&mime_type=video_mp4&qs=0&rc=OGU0O2Y0OWY2NmZoZzk5aEBpamw8aGw5cm5sdTMzZjczM0A0MDZjYmNeNmMxNGAyLTQvYSNeYmw0MmQ0cm5gLS1kMWNzcw%3D%3D&btag=e000a0000&expire=1733357218&l=202412041801294B1E5C8317906016A952&ply_type=2&policy=2&signature=a26e3286cef3a6e2a71d72708b02afa0&tk=tt_chain_token",
            "https://www.tiktok.com/aweme/v1/play/?faid=1988&file_id=2e76065dce7c43f39ca6f1ecf8913b75&is_play_url=1&item_id=7418891684420930849&line=0&ply_type=2&redirect=0&signaturev3=dmlkZW9faWQ7ZmlsZV9pZDtpdGVtX2lkLjFkM2U0ZTgzZTFlY2ZjYzRhNzA0ZDM0NTJiMzk0ODYw&tk=tt_chain_token&vidc=useast2a&video_id=v0f044gc0000crqiuk7og65i7eo9eiag"
          ],
          "UrlKey": "v0f044gc0000crqiuk7og65i7eo9eiag_h264_540p_283859",
          "FileHash": "ec575d6457bad3decb8ed38d0666d65c",
          "FileCs": "c:0-269784-7522"
        },
        "CodecType": "h264",
        "MVMAF": "\"\""
      },
      {
        "Bitrate": 198383,
        "QualityType": 14,
        "GearName": "adapt_lower_720_1",
        "PlayAddr": {
          "DataSize": "8134998",
          "Width": 720,
          "Height": 1282,
          "Uri": "v0f044gc0000crqiuk7og65i7eo9eiag",
          "UrlList": [
            "https://v16-webapp-prime.tiktok.com/video/tos/useast2a/tos-useast2a-ve-0068-euttp/ogEq9m2dEDeSAF4HugPQhQDdvQP9BqDkEIMfRk/?a=1988&bti=ODszNWYuMDE6&ch=0&cr=3&dr=0&lr=all&cd=0%7C0%7C0%7C&cv=1&br=386&bt=193&cs=2&ds=3&eid=256&ft=4fUEKMFx8Zmo0KhCqb4jVk7CrpWrKsd.&mime_type=video_mp4&qs=14&rc=O2Y1ZmU4OTU3OTYzNWUzZ0Bpamw8aGw5cm5sdTMzZjczM0A1Ni4yMjIwNV8xXmI1YzRiYSNeYmw0MmQ0cm5gLS1kMWNzcw%3D%3D&btag=e000a0000&expire=1733357218&l=202412041801294B1E5C8317906016A952&ply_type=2&policy=2&signature=0ef3b619db1f4644cd562b150983bacb&tk=tt_chain_token",
            "https://v19-webapp-prime.tiktok.com/video/tos/useast2a/tos-useast2a-ve-0068-euttp/ogEq9m2dEDeSAF4HugPQhQDdvQP9BqDkEIMfRk/?a=1988&bti=ODszNWYuMDE6&ch=0&cr=3&dr=0&lr=all&cd=0%7C0%7C0%7C&cv=1&br=386&bt=193&cs=2&ds=3&eid=256&ft=4fUEKMFx8Zmo0KhCqb4jVk7CrpWrKsd.&mime_type=video_mp4&qs=14&rc=O2Y1ZmU4OTU3OTYzNWUzZ0Bpamw8aGw5cm5sdTMzZjczM0A1Ni4yMjIwNV8xXmI1YzRiYSNeYmw0MmQ0cm5gLS1kMWNzcw%3D%3D&btag=e000a0000&expire=1733357218&l=202412041801294B1E5C8317906016A952&ply_type=2&policy=2&signature=0ef3b619db1f4644cd562b150983bacb&tk=tt_chain_token",
            "https://www.tiktok.com/aweme/v1/play/?faid=1988&file_id=ed70fb82e0a346b48236555b5c129c88&is_play_url=1&item_id=7418891684420930849&line=0&ply_type=2&redirect=0&signaturev3=dmlkZW9faWQ7ZmlsZV9pZDtpdGVtX2lkLjg3NmQ4ZDhlMzQ4ZDJlMWE3M2MzYmY5YjY4MGI5NTZi&tk=tt_chain_token&vidc=useast2a&video_id=v0f044gc0000crqiuk7og65i7eo9eiag"
          ],
          "UrlKey": "v0f044gc0000crqiuk7og65i7eo9eiag_bytevc1_720p_198383",
          "FileHash": "a4233ce1628ab6162c0d3debc2629b9b",
          "FileCs": "c:0-271166-d4e6"
        },
        "CodecType": "h265_hvc1",
        "MVMAF": "\"{\\\"v2.0\\\": {\\\"ori\\\": {\\\"v1080\\\": 89.746, \\\"v960\\\": 92.194, \\\"v864\\\": 93.409, \\\"v720\\\": 96.216}, \\\"srv1\\\": {\\\"v1080\\\": 99.154, \\\"v960\\\": 99.256, \\\"v864\\\": 99.515, \\\"v720\\\": 100.0}}}\""
      },
      {
        "Bitrate": 179099,
        "QualityType": 24,
        "GearName": "lower_540_0",
        "PlayAddr": {
          "DataSize": "7344255",
          "Width": 576,
          "Height": 1026,
          "Uri": "v0f044gc0000crqiuk7og65i7eo9eiag",
          "UrlList": [
            "https://v16-webapp-prime.tiktok.com/video/tos/useast2a/tos-useast2a-ve-0068c001-euttp/oEPH5ivEBwA1iEUOVSExTZ0M7yQvIxATXBCUO/?a=1988&bti=ODszNWYuMDE6&ch=0&cr=3&dr=0&lr=all&cd=0%7C0%7C0%7C&cv=1&br=348&bt=174&cs=0&ds=6&ft=4fUEKMFx8Zmo0KhCqb4jVk7CrpWrKsd.&mime_type=video_mp4&qs=4&rc=MzlpOzppO2U6NTppZDU4Z0Bpamw8aGw5cm5sdTMzZjczM0A0LjA1M18uNTYxNWJeNmNiYSNeYmw0MmQ0cm5gLS1kMWNzcw%3D%3D&btag=e000a0000&expire=1733357218&l=202412041801294B1E5C8317906016A952&ply_type=2&policy=2&signature=f2ae5ca4142cb2823d9550d7ec3dbf20&tk=tt_chain_token",
            "https://v19-webapp-prime.tiktok.com/video/tos/useast2a/tos-useast2a-ve-0068c001-euttp/oEPH5ivEBwA1iEUOVSExTZ0M7yQvIxATXBCUO/?a=1988&bti=ODszNWYuMDE6&ch=0&cr=3&dr=0&lr=all&cd=0%7C0%7C0%7C&cv=1&br=348&bt=174&cs=0&ds=6&ft=4fUEKMFx8Zmo0KhCqb4jVk7CrpWrKsd.&mime_type=video_mp4&qs=4&rc=MzlpOzppO2U6NTppZDU4Z0Bpamw8aGw5cm5sdTMzZjczM0A0LjA1M18uNTYxNWJeNmNiYSNeYmw0MmQ0cm5gLS1kMWNzcw%3D%3D&btag=e000a0000&expire=1733357218&l=202412041801294B1E5C8317906016A952&ply_type=2&policy=2&signature=f2ae5ca4142cb2823d9550d7ec3dbf20&tk=tt_chain_token",
            "https://www.tiktok.com/aweme/v1/play/?faid=1988&file_id=edf592aaef8742978b18bf67883f1670&is_play_url=1&item_id=7418891684420930849&line=0&ply_type=2&redirect=0&signaturev3=dmlkZW9faWQ7ZmlsZV9pZDtpdGVtX2lkLmQ0Njc1ZDM4YjNiMzc4ZTIwOWMxZTE3NDhlN2ZmNGYz&tk=tt_chain_token&vidc=useast2a&video_id=v0f044gc0000crqiuk7og65i7eo9eiag"
          ],
          "UrlKey": "v0f044gc0000crqiuk7og65i7eo9eiag_h264_540p_179099",
          "FileHash": "e96ebe762254f1140d4e02dd18955d69",
          "FileCs": "c:0-269784-5bc6"
        },
        "CodecType": "h264",
        "MVMAF": "\"\""
      },
      {
        "Bitrate": 153959,
        "QualityType": 28,
        "GearName": "adapt_540_1",
        "PlayAddr": {
          "DataSize": "6313337",
          "Width": 576,
          "Height": 1026,
          "Uri": "v0f044gc0000crqiuk7og65i7eo9eiag",
          "UrlList": [
            "https://v16-webapp-prime.tiktok.com/video/tos/useast2a/tos-useast2a-ve-0068c001-euttp/oI2cTgMqmvDZfkEqBkFEQ9DQE9ARlJCIQdfuPS/?a=1988&bti=ODszNWYuMDE6&ch=0&cr=3&dr=0&lr=all&cd=0%7C0%7C0%7C&cv=1&br=300&bt=150&cs=2&ds=6&eid=256&ft=4fUEKMFx8Zmo0KhCqb4jVk7CrpWrKsd.&mime_type=video_mp4&qs=11&rc=NzhmOzk2aWY1Zzg3PGhmM0Bpamw8aGw5cm5sdTMzZjczM0BjX2AvMTMyNjAxXi5eYTFhYSNeYmw0MmQ0cm5gLS1kMWNzcw%3D%3D&btag=e000a0000&expire=1733357218&l=202412041801294B1E5C8317906016A952&ply_type=2&policy=2&signature=8f9c36572951d50a0ea8b804390c3444&tk=tt_chain_token",
            "https://v19-webapp-prime.tiktok.com/video/tos/useast2a/tos-useast2a-ve-0068c001-euttp/oI2cTgMqmvDZfkEqBkFEQ9DQE9ARlJCIQdfuPS/?a=1988&bti=ODszNWYuMDE6&ch=0&cr=3&dr=0&lr=all&cd=0%7C0%7C0%7C&cv=1&br=300&bt=150&cs=2&ds=6&eid=256&ft=4fUEKMFx8Zmo0KhCqb4jVk7CrpWrKsd.&mime_type=video_mp4&qs=11&rc=NzhmOzk2aWY1Zzg3PGhmM0Bpamw8aGw5cm5sdTMzZjczM0BjX2AvMTMyNjAxXi5eYTFhYSNeYmw0MmQ0cm5gLS1kMWNzcw%3D%3D&btag=e000a0000&expire=1733357218&l=202412041801294B1E5C8317906016A952&ply_type=2&policy=2&signature=8f9c36572951d50a0ea8b804390c3444&tk=tt_chain_token",
            "https://www.tiktok.com/aweme/v1/play/?faid=1988&file_id=d04cdea914a54d329c5f634628ccb5f4&is_play_url=1&item_id=7418891684420930849&line=0&ply_type=2&redirect=0&signaturev3=dmlkZW9faWQ7ZmlsZV9pZDtpdGVtX2lkLjM2MmNlODhlZWJlZTJkZDJjOWYyMmI5NWZkYjI4MTIw&tk=tt_chain_token&vidc=useast2a&video_id=v0f044gc0000crqiuk7og65i7eo9eiag"
          ],
          "UrlKey": "v0f044gc0000crqiuk7og65i7eo9eiag_bytevc1_540p_153959",
          "FileHash": "f8cabb62cba8bd9ef4b5d1644827aaa4",
          "FileCs": "c:0-271166-fde7"
        },
        "CodecType": "h265_hvc1",
        "MVMAF": "\"{\\\"v2.0\\\": {\\\"ori\\\": {\\\"v1080\\\": 85.6, \\\"v960\\\": 89.134, \\\"v864\\\": 90.112, \\\"v720\\\": 92.792}, \\\"srv1\\\": {\\\"v1080\\\": 98.18, \\\"v960\\\": 98.661, \\\"v864\\\": 99.963, \\\"v720\\\": 99.912}}}\""
      }
    ],
    "VQScore": "73.42",
    "claInfo": {
      "hasOriginalAudio": true,
      "enableAutoCaption": true,
      "originalLanguageInfo": {
        "language": "deu-DE",
        "languageID": "20",
        "languageCode": "de"
      },
      "captionInfos": [
        {
          "language": "deu-DE",
          "languageID": "20",
          "url": "https://v16-webapp.tiktok.com/920a53af7877fe079937ab6d267fb4d9/6750eea2/video/tos/useast2a/tos-useast2a-v-0037-euttp/d07377531a1e4639b55cac8414cebe39/?a=1988&bti=ODszNWYuMDE6&ch=0&cr=3&dr=0&lr=all&cd=0%7C0%7C0%7C&cv=1&br=6700&bt=3350&ds=4&ft=4b~OyMFx8Zmo0KhCqb4jVk7CrpWrKsd.&mime_type=video_mp4&qs=13&rc=amw8aGw5cm5sdTMzZjczM0Bpamw8aGw5cm5sdTMzZjczM0BeYmw0MmQ0cm5gLS1kMWNzYSNeYmw0MmQ0cm5gLS1kMWNzcw%3D%3D&l=202412041801294B1E5C8317906016A952&btag=e00060000",
          "expire": "1733357218",
          "captionFormat": "webvtt",
          "isAutoGen": true,
          "subID": "1629357531",
          "claSubtitleID": "7418897589384596257",
          "languageCode": "de",
          "isOriginalCaption": true,
          "urlList": [
            "https://v16-webapp.tiktok.com/920a53af7877fe079937ab6d267fb4d9/6750eea2/video/tos/useast2a/tos-useast2a-v-0037-euttp/d07377531a1e4639b55cac8414cebe39/?a=1988&bti=ODszNWYuMDE6&ch=0&cr=3&dr=0&lr=all&cd=0%7C0%7C0%7C&cv=1&br=6700&bt=3350&ds=4&ft=4b~OyMFx8Zmo0KhCqb4jVk7CrpWrKsd.&mime_type=video_mp4&qs=13&rc=amw8aGw5cm5sdTMzZjczM0Bpamw8aGw5cm5sdTMzZjczM0BeYmw0MmQ0cm5gLS1kMWNzYSNeYmw0MmQ0cm5gLS1kMWNzcw%3D%3D&l=202412041801294B1E5C8317906016A952&btag=e00060000",
            "https://v16-webapp.tiktok.com/920a53af7877fe079937ab6d267fb4d9/6750eea2/video/tos/useast2a/tos-useast2a-v-0037-euttp/d07377531a1e4639b55cac8414cebe39/?a=1988&bti=ODszNWYuMDE6&ch=0&cr=3&dr=0&lr=all&cd=0%7C0%7C0%7C&cv=1&br=6700&bt=3350&ds=4&ft=4b~OyMFx8Zmo0KhCqb4jVk7CrpWrKsd.&mime_type=video_mp4&qs=13&rc=amw8aGw5cm5sdTMzZjczM0Bpamw8aGw5cm5sdTMzZjczM0BeYmw0MmQ0cm5gLS1kMWNzYSNeYmw0MmQ0cm5gLS1kMWNzcw%3D%3D&l=202412041801294B1E5C8317906016A952&btag=e00060000",
            "https://vas-useast2a.tiktokv.com/tiktok/v1/subtitle/url?aid=1988&format=webvtt&language=deu-DE&sign=441d3ef7c4d243bcee19b0bcf23604ed&version=1%3Awhisper_lid&vid=v0f044gc0000crqiuk7og65i7eo9eiag"
          ],
          "variant": "whisper_lid",
          "subtitleType": "1"
        }
      ],
      "captionsType": "1",
      "noCaptionReason": null
    }
  },
  "author": {
    "id": "6692430541223330822",
    "shortId": "",
    "uniqueId": "nino00909",
    "nickname": "Tom",
    "avatarLarger": "https://p16-sign-useast2a.tiktokcdn.com/tos-useast2a-avt-0068-euttp/da9baf9533eafd62c6570fd88db72dba~c5_1080x1080.jpeg?lk3s=a5d48078&nonce=34892&refresh_token=9fe7e1f249c0fbc6b0a648c67f66be3e&x-expires=1733508000&x-signature=YU1r4ww3ETJp3FzqhgGYQk1SKR8%3D&shp=a5d48078&shcp=81f88b70",
    "avatarMedium": "https://p16-sign-useast2a.tiktokcdn.com/tos-useast2a-avt-0068-euttp/da9baf9533eafd62c6570fd88db72dba~c5_720x720.jpeg?lk3s=a5d48078&nonce=73926&refresh_token=7b2d873d6a9a05dae4174fc005007898&x-expires=1733508000&x-signature=n0zJJa9HAU4sYO0uEWxLVasTsjo%3D&shp=a5d48078&shcp=81f88b70",
    "avatarThumb": "https://p16-sign-useast2a.tiktokcdn.com/tos-useast2a-avt-0068-euttp/da9baf9533eafd62c6570fd88db72dba~c5_100x100.jpeg?lk3s=a5d48078&nonce=6733&refresh_token=8238f8748795d59f81f99fe3648dee35&x-expires=1733508000&x-signature=OSk8Z1lp8nKa8j%2Fk2e%2FuAT3NqfM%3D&shp=a5d48078&shcp=81f88b70",
    "signature": "Für die Zukunft und Wohlstand im Land! I",
    "createTime": 0,
    "verified": false,
    "secUid": "MS4wLjABAAAAdiKgicMGA2Vk17dd0eC34Bgw2XRbJoUKcELJDTQk2_ROQQc-JFnTIHZlsY3uGVCy",
    "ftc": false,
    "relation": 0,
    "openFavorite": false,
    "commentSetting": 0,
    "duetSetting": 0,
    "stitchSetting": 0,
    "privateAccount": false,
    "secret": false,
    "isADVirtual": false,
    "roomId": "",
    "uniqueIdModifyTime": 0,
    "ttSeller": false,
    "downloadSetting": 3,
    "recommendReason": "",
    "nowInvitationCardUrl": "",
    "nickNameModifyTime": 0,
    "isEmbedBanned": false,
    "canExpPlaylist": false,
    "suggestAccountBind": false
  },
  "music": {
    "id": "7418891795617893152",
    "title": "Originalton",
    "playUrl": "https://v77.tiktokcdn-eu.com/36084f6bb17b695e2a4ca9279fcf1a86/6750a852/video/tos/useast2a/tos-useast2a-v-2370-euttp/oYxeMmAbfCBuQ4DPUtw1LvMQWFJ9T91FGPEIDu/?a=1233&bti=ODszNWYuMDE6&ch=0&cr=0&dr=0&er=0&lr=default&cd=0%7C0%7C0%7C0&br=250&bt=125&ft=.NpOcInz7ThY_VIOXq8Zmo&mime_type=audio_mpeg&qs=6&rc=NjczaWZnPDk0aDc2ZTNoOkBpM2tyeHg5cm1tdTMzZjU8M0AyMTEwNmJgNTQxXjMwYC0wYSNrYS9rMmRzMm5gLS1kMWNzcw%3D%3D&vvpl=1&l=202412041801294B1E5C8317906016A952&btag=e000a0000",
    "coverLarge": "https://p16-sign-useast2a.tiktokcdn.com/tos-useast2a-avt-0068-euttp/da9baf9533eafd62c6570fd88db72dba~c5_1080x1080.jpeg?lk3s=a5d48078&nonce=34892&refresh_token=9fe7e1f249c0fbc6b0a648c67f66be3e&x-expires=1733508000&x-signature=YU1r4ww3ETJp3FzqhgGYQk1SKR8%3D&shp=a5d48078&shcp=81f88b70",
    "coverMedium": "https://p16-sign-useast2a.tiktokcdn.com/tos-useast2a-avt-0068-euttp/da9baf9533eafd62c6570fd88db72dba~c5_720x720.jpeg?lk3s=a5d48078&nonce=73926&refresh_token=7b2d873d6a9a05dae4174fc005007898&x-expires=1733508000&x-signature=n0zJJa9HAU4sYO0uEWxLVasTsjo%3D&shp=a5d48078&shcp=81f88b70",
    "coverThumb": "https://p16-sign-useast2a.tiktokcdn.com/tos-useast2a-avt-0068-euttp/da9baf9533eafd62c6570fd88db72dba~c5_100x100.jpeg?lk3s=a5d48078&nonce=6733&refresh_token=8238f8748795d59f81f99fe3648dee35&x-expires=1733508000&x-signature=OSk8Z1lp8nKa8j%2Fk2e%2FuAT3NqfM%3D&shp=a5d48078&shcp=81f88b70",
    "authorName": "Tom",
    "original": false,
    "duration": 328,
    "scheduleSearchTime": 0,
    "collected": false,
    "preciseDuration": {
      "preciseDuration": 328.09793,
      "preciseShootDuration": 328.09793,
      "preciseAuditionDuration": 328.09793,
      "preciseVideoDuration": 328.09793
    }
  },
  "challenges": [
    {
      "id": "6391435",
      "title": "afd",
      "desc": "",
      "profileLarger": "",
      "profileMedium": "",
      "profileThumb": "",
      "coverLarger": "",
      "coverMedium": "",
      "coverThumb": ""
    },
    {
      "id": "1676890409828358",
      "title": "afddeutschland",
      "desc": "",
      "profileLarger": "",
      "profileMedium": "",
      "profileThumb": "",
      "coverLarger": "",
      "coverMedium": "",
      "coverThumb": ""
    },
    {
      "id": "1689319007649810",
      "title": "afdbundestag",
      "desc": "",
      "profileLarger": "",
      "profileMedium": "",
      "profileThumb": "",
      "coverLarger": "",
      "coverMedium": "",
      "coverThumb": ""
    },
    {
      "id": "1691947213472774",
      "title": "stefanbrandner",
      "desc": "",
      "profileLarger": "",
      "profileMedium": "",
      "profileThumb": "",
      "coverLarger": "",
      "coverMedium": "",
      "coverThumb": ""
    },
    {
      "id": "22325311",
      "title": "bundestag",
      "desc": "",
      "profileLarger": "",
      "profileMedium": "",
      "profileThumb": "",
      "coverLarger": "",
      "coverMedium": "",
      "coverThumb": ""
    },
    {
      "id": "7107253141413822469",
      "title": "ampelregierungmussweg",
      "desc": "",
      "profileLarger": "",
      "profileMedium": "",
      "profileThumb": "",
      "coverLarger": "",
      "coverMedium": "",
      "coverThumb": ""
    },
    {
      "id": "7345842326977118241",
      "title": "bürokratieentlastungsgesetz",
      "desc": "",
      "profileLarger": "",
      "profileMedium": "",
      "profileThumb": "",
      "coverLarger": "",
      "coverMedium": "",
      "coverThumb": ""
    },
    {
      "id": "15837878",
      "title": "aktuell",
      "desc": "",
      "profileLarger": "",
      "profileMedium": "",
      "profileThumb": "",
      "coverLarger": "",
      "coverMedium": "",
      "coverThumb": ""
    },
    {
      "id": "204862",
      "title": "deutschland",
      "desc": "🇩🇪  musical.ly Deutschland 🇩🇪\n\nGib uns ein LIKE und werde mit etwas Glück gefeatured!!! 💛\n\nFür Features den Hashtag #Deutschland nicht vergessen! ☝",
      "profileLarger": "",
      "profileMedium": "",
      "profileThumb": "",
      "coverLarger": "",
      "coverMedium": "",
      "coverThumb": ""
    },
    {
      "id": "5457735",
      "title": "fürdich",
      "desc": "Ein Song der nie vergeht!\n\nMacht mit beim neuen Remix von @diemai 😍  \nEinfach ein Duett machen zur aktuellen Single &amp;amp;amp;amp;amp;amp;amp;amp;amp;amp;quot;Für Dich&amp;amp;amp;amp;amp;amp;amp;amp;amp;amp;quot; und ein live.ly Meet&amp;amp;amp;amp;amp;amp;amp;amp;amp;amp;amp;Greet mit Vanessa Mai gewinnen 🔥",
      "profileLarger": "",
      "profileMedium": "",
      "profileThumb": "",
      "coverLarger": "",
      "coverMedium": "",
      "coverThumb": ""
    },
    {
      "id": "229207",
      "title": "fyp",
      "desc": "",
      "profileLarger": "",
      "profileMedium": "",
      "profileThumb": "",
      "coverLarger": "",
      "coverMedium": "",
      "coverThumb": ""
    },
    {
      "id": "17127393",
      "title": "politik",
      "desc": "",
      "profileLarger": "",
      "profileMedium": "",
      "profileThumb": "",
      "coverLarger": "",
      "coverMedium": "",
      "coverThumb": ""
    },
    {
      "id": "1671525037102081",
      "title": "politiktiktok",
      "desc": "",
      "profileLarger": "",
      "profileMedium": "",
      "profileThumb": "",
      "coverLarger": "",
      "coverMedium": "",
      "coverThumb": ""
    }
  ],
  "stats": {
    "diggCount": 5582,
    "shareCount": 661,
    "commentCount": 774,
    "playCount": 77300,
    "collectCount": "474"
  },
  "statsV2": {
    "diggCount": "5582",
    "shareCount": "661",
    "commentCount": "774",
    "playCount": "77300",
    "collectCount": "474",
    "repostCount": "0"
  },
  "warnInfo": [],
  "originalItem": false,
  "officalItem": false,
  "textExtra": [
    {
      "awemeId": "",
      "start": 61,
      "end": 65,
      "hashtagId": "6391435",
      "hashtagName": "afd",
      "type": 1,
      "subType": 0,
      "isCommerce": false
    },
    {
      "awemeId": "",
      "start": 66,
      "end": 81,
      "hashtagId": "1676890409828358",
      "hashtagName": "afddeutschland",
      "type": 1,
      "subType": 0,
      "isCommerce": false
    },
    {
      "awemeId": "",
      "start": 82,
      "end": 95,
      "hashtagId": "1689319007649810",
      "hashtagName": "afdbundestag",
      "type": 1,
      "subType": 0,
      "isCommerce": false
    },
    {
      "awemeId": "",
      "start": 96,
      "end": 111,
      "hashtagId": "1691947213472774",
      "hashtagName": "stefanbrandner",
      "type": 1,
      "subType": 0,
      "isCommerce": false
    },
    {
      "awemeId": "",
      "start": 112,
      "end": 122,
      "hashtagId": "22325311",
      "hashtagName": "bundestag",
      "type": 1,
      "subType": 0,
      "isCommerce": false
    },
    {
      "awemeId": "",
      "start": 123,
      "end": 145,
      "hashtagId": "7107253141413822469",
      "hashtagName": "ampelregierungmussweg",
      "type": 1,
      "subType": 0,
      "isCommerce": false
    },
    {
      "awemeId": "",
      "start": 148,
      "end": 176,
      "hashtagId": "7345842326977118241",
      "hashtagName": "bürokratieentlastungsgesetz",
      "type": 1,
      "subType": 0,
      "isCommerce": false
    },
    {
      "awemeId": "",
      "start": 177,
      "end": 185,
      "hashtagId": "15837878",
      "hashtagName": "aktuell",
      "type": 1,
      "subType": 0,
      "isCommerce": false
    },
    {
      "awemeId": "",
      "start": 186,
      "end": 198,
      "hashtagId": "204862",
      "hashtagName": "deutschland",
      "type": 1,
      "subType": 0,
      "isCommerce": false
    },
    {
      "awemeId": "",
      "start": 199,
      "end": 207,
      "hashtagId": "5457735",
      "hashtagName": "fürdich",
      "type": 1,
      "subType": 0,
      "isCommerce": false
    },
    {
      "awemeId": "",
      "start": 208,
      "end": 212,
      "hashtagId": "229207",
      "hashtagName": "fyp",
      "type": 1,
      "subType": 0,
      "isCommerce": false
    },
    {
      "awemeId": "",
      "start": 213,
      "end": 221,
      "hashtagId": "17127393",
      "hashtagName": "politik",
      "type": 1,
      "subType": 0,
      "isCommerce": false
    },
    {
      "awemeId": "",
      "start": 222,
      "end": 236,
      "hashtagId": "1671525037102081",
      "hashtagName": "politiktiktok",
      "type": 1,
      "subType": 0,
      "isCommerce": false
    }
  ],
  "secret": false,
  "forFriend": false,
  "digged": false,
  "itemCommentStatus": 0,
  "takeDown": 0,
  "effectStickers": [],
  "authorStats": {
    "followerCount": 39000,
    "followingCount": 219,
    "heart": 607700,
    "heartCount": 607700,
    "videoCount": 321,
    "diggCount": 13000,
    "friendCount": 0
  },
  "privateItem": false,
  "duetEnabled": true,
  "stickersOnItem": [],
  "shareEnabled": true,
  "comments": [],
  "duetDisplay": 0,
  "stitchDisplay": 0,
  "indexEnabled": true,
  "locationCreated": "DE",
  "contentLocation": {
    "address": {
      "addressCountry": "",
      "addressLocality": "",
      "addressRegion": "",
      "streetAddress": "Germany, Europe"
    }
  },
  "poi": {
    "name": "Germany",
    "address": "Europe",
    "city": "",
    "province": "",
    "country": "",
    "id": "22535865200906208",
    "fatherPoiId": "",
    "fatherPoiName": "",
    "type": 0,
    "category": "Place and Address",
    "cityCode": "6547389",
    "countryCode": "2921044",
    "ttTypeCode": "19a3a1",
    "typeCode": "",
    "ttTypeNameTiny": "Country",
    "ttTypeNameMedium": "Places",
    "ttTypeNameSuper": "Place and Address"
  },
  "suggestedWords": [
    "afd bundestag",
    "Afd",
    "afd deutschland",
    "Afd Fraktion Bundestag",
    "afd germany",
    "politik deutschland",
    "afd wähler",
    "bundestag"
  ],
  "contents": [
    {
      "desc": "26.09.24 Aktuelle Stunde im Bundestag. Stefan Brandener AfD. #afd #afddeutschland #afdbundestag #stefanbrandner #bundestag #ampelregierungmussweg # #bürokratieentlastungsgesetz #aktuell #deutschland #fürdich #fyp #politik #politiktiktok ",
      "textExtra": [
        {
          "awemeId": "",
          "start": 61,
          "end": 65,
          "hashtagId": "6391435",
          "hashtagName": "afd",
          "type": 1,
          "subType": 0,
          "isCommerce": false
        },
        {
          "awemeId": "",
          "start": 66,
          "end": 81,
          "hashtagId": "1676890409828358",
          "hashtagName": "afddeutschland",
          "type": 1,
          "subType": 0,
          "isCommerce": false
        },
        {
          "awemeId": "",
          "start": 82,
          "end": 95,
          "hashtagId": "1689319007649810",
          "hashtagName": "afdbundestag",
          "type": 1,
          "subType": 0,
          "isCommerce": false
        },
        {
          "awemeId": "",
          "start": 96,
          "end": 111,
          "hashtagId": "1691947213472774",
          "hashtagName": "stefanbrandner",
          "type": 1,
          "subType": 0,
          "isCommerce": false
        },
        {
          "awemeId": "",
          "start": 112,
          "end": 122,
          "hashtagId": "22325311",
          "hashtagName": "bundestag",
          "type": 1,
          "subType": 0,
          "isCommerce": false
        },
        {
          "awemeId": "",
          "start": 123,
          "end": 145,
          "hashtagId": "7107253141413822469",
          "hashtagName": "ampelregierungmussweg",
          "type": 1,
          "subType": 0,
          "isCommerce": false
        },
        {
          "awemeId": "",
          "start": 148,
          "end": 176,
          "hashtagId": "7345842326977118241",
          "hashtagName": "bürokratieentlastungsgesetz",
          "type": 1,
          "subType": 0,
          "isCommerce": false
        },
        {
          "awemeId": "",
          "start": 177,
          "end": 185,
          "hashtagId": "15837878",
          "hashtagName": "aktuell",
          "type": 1,
          "subType": 0,
          "isCommerce": false
        },
        {
          "awemeId": "",
          "start": 186,
          "end": 198,
          "hashtagId": "204862",
          "hashtagName": "deutschland",
          "type": 1,
          "subType": 0,
          "isCommerce": false
        },
        {
          "awemeId": "",
          "start": 199,
          "end": 207,
          "hashtagId": "5457735",
          "hashtagName": "fürdich",
          "type": 1,
          "subType": 0,
          "isCommerce": false
        },
        {
          "awemeId": "",
          "start": 208,
          "end": 212,
          "hashtagId": "229207",
          "hashtagName": "fyp",
          "type": 1,
          "subType": 0,
          "isCommerce": false
        },
        {
          "awemeId": "",
          "start": 213,
          "end": 221,
          "hashtagId": "17127393",
          "hashtagName": "politik",
          "type": 1,
          "subType": 0,
          "isCommerce": false
        },
        {
          "awemeId": "",
          "start": 222,
          "end": 236,
          "hashtagId": "1671525037102081",
          "hashtagName": "politiktiktok",
          "type": 1,
          "subType": 0,
          "isCommerce": false
        }
      ]
    }
  ],
  "diversificationId": 10083,
  "collected": false,
  "channelTags": [],
  "item_control": {
    "can_repost": true
  },
  "IsAigc": false,
  "AIGCDescription": "",
  "backendSourceEventTracking": ""
}